AUTHORS
ChangeLog
LICENSE
PKG-INFO
README.rst
requirements.txt
setup.cfg
setup.py
bservices/__init__.py
bservices/exception.py
bservices/middleware.py
bservices/wsgi.py
bservices.egg-info/PKG-INFO
bservices.egg-info/SOURCES.txt
bservices.egg-info/dependency_links.txt
bservices.egg-info/entry_points.txt
bservices.egg-info/not-zip-safe
bservices.egg-info/pbr.json
bservices.egg-info/requires.txt
bservices.egg-info/top_level.txt
bservices/contrib/__init__.py
bservices/contrib/api_version.py
bservices/contrib/daemon.py
bservices/contrib/server.py
bservices/db/__init__.py
bservices/db/sqlalchemy/__init__.py
bservices/examples/__init__.py
bservices/examples/pool_server_example.py
bservices/examples/task_server_example.py
bservices/examples/tcp_server_example.py
bservices/examples/wsgi_server_example.py
bservices/examples/db/__init__.py
bservices/examples/db/api.py
bservices/examples/db/sqlalchemy/__init__.py
bservices/examples/db/sqlalchemy/api.py
bservices/examples/db/sqlalchemy/models.py